{
  "id": "4257d1143fb12e0b",
  "title": "Toward Personalized Darts Training: A Data-Driven Framework Based on Skeleton-Based Biomechanical Analysis and Motion Modeling",
  "link": "https://arxiv.org/abs/2604.01130",
  "summary": "arXiv:2604.01130v3 Announce Type: replace \nAbstract: As sports training becomes more data-driven, traditional dart coaching based mainly on experience and visual observation is increasingly inadequate for high-precision, goal-oriented movements. Although prior studies have highlighted the importance of release parameters, joint motion, and coordination in dart throwing, most quantitative methods still focus on local variables, single-release metrics, or static template matching. These approaches offer limited support for personalized training and often overlook useful movement variability. This paper presents a data-driven dart training assistance system. The system creates a closed-loop framework spanning motion capture, feature modeling, and personalized feedback. Dart-throwing data were collected in markerless conditions using a Kinect 2.0 depth sensor and an optical camera. Eighteen kinematic features were extracted from four biomechanical dimensions: three-link coordination, release velocity, multi-joint angular configuration, and postural stability. Two modules were developed: a personalized optimal throwing trajectory model that combines historical high-quality samples with the minimum jerk criterion, and a motion deviation diagnosis and recommendation model based on z-scores and hierarchical logic. A total of 2,396 throwing samples from professional and non-professional athletes were collected. Results show that the system generates smooth personalized reference trajectories consistent with natural human movement. Case studies indicate that it can detect poor trunk stability, abnormal elbow displacement, and imbalanced velocity control, then provide targeted recommendations. The framework shifts dart evaluation from deviation from a uniform standard to deviation from an individual's optimal control range, improving personalization and interpretability for darts training and other high-precision target sports.",
  "feed": "arxiv-cs-LG"
}