{
  "id": "c6fdd9ae488702db",
  "title": "How is your org/company measuring the impact of AI adoption?",
  "link": "https://lobste.rs/s/bzcjrl/how_is_your_org_company_measuring_impact",
  "summary": "<p>Title says it best. We're at a point in our AI journey where tools are deployed, infrastructure stood up, features are shipping, and naturally, costs associated with AI usage are rising.</p>\n<p>We're now being asked to estimate the impact of AI in our daily work.</p>\n<p>How are you doing this at your company or within you org/department?</p>",
  "feed": "lobsters-ai"
}