{
  "id": "631ec361eadc8483",
  "title": "Approximation of the Basset force in the Maxey-Riley-Gatignol equations via universal differential equations",
  "link": "https://arxiv.org/abs/2604.08194",
  "summary": "arXiv:2604.08194v1 Announce Type: new \nAbstract: The Maxey-Riley-Gatignol equations (MaRGE) model the motion of spherical inertial particles in a fluid. They contain the Basset force, an integral term which models history effects due to the formation of wakes and boundary layer effects. This causes the force that acts on a particle to depend on its past trajectory and complicates the numerical solution of MaRGE. Therefore, the Basset force is often neglected, despite substantial evidence that it has both quantitative and qualitative impact on the movement patterns of modelled particles. Using the concept of universal differential equations, we propose an approximation of the history term via neural networks which approximates MaRGE by a system of ordinary differential equations that can be solved with standard numerical solvers like Runge-Kutta methods.",
  "feed": "arxiv-cs-LG"
}